MoireStudio/__init__.py
MoireStudio/driver.py
MoireStudio/kp_parameter.py
MoireStudio/read_tb_model.py
MoireStudio/simple_func.py
MoireStudio/solver.py
MoireStudio/tb_model.py
MoireStudio/tb_parameter.py
MoireStudio/twist_geometry.py
MoireStudio/twist_kp.py
MoireStudio/twist_relaxation.py
MoireStudio/twist_tb.py
MoireStudio/twist_viz.py
moirestudio-1.0.1.dist-info/licenses/LICENSE
moirestudio-1.0.1.dist-info/METADATA
moirestudio-1.0.1.dist-info/WHEEL
moirestudio-1.0.1.dist-info/entry_points.txt
moirestudio-1.0.1.dist-info/top_level.txt
moirestudio-1.0.1.dist-info/RECORD
