Metadata-Version: 2.4
Name: MoireStudio
Version: 1.0.1
Summary: Universal Twisted Electronic Structure Calculation Package
Author: Junxi Yu
License: Copyright (C) <2026> <Junxi Yu>
Requires-Python: >=3.10
License-File: LICENSE
Requires-Dist: numpy>=1.23
Requires-Dist: scipy>=1.9
Requires-Dist: matplotlib>=3.7
Dynamic: license-file
